{"id": "hLQl3WQQoQ0", "uploader": "AdeleVEVO", "uploader_id": "AdeleVEVO", "uploader_url": "http://www.youtube.com/user/AdeleVEVO", "upload_date": "20110929", "license": "Standard YouTube License", "creator": null, "title": "Adele - Someone Like You", "alt_title": null, "thumbnail": "https://i.ytimg.com/vi/hLQl3WQQoQ0/maxresdefault.jpg", "description": "Buy/Listen 25: http://smarturl.it/25Album?IQid=yt\nBuy/Listen 21: http://smarturl.it/Adele21Album?IQid=yt\nBuy/Listen 19: http://smarturl.it/19Album?IQid=yt\n\nFollow Adele on:\nFacebook - http://facebook.com/adele\nTwitter - http://twitter.com/adele\nInstagram - http://instagram.com/adele\nSubscribe to the Adele VEVO Channel - http://smarturl.it/SubscribeAdele?IQid=yt\nVisit - www.adele.com", "categories": ["Music"], "tags": ["Adele", "Someone", "Like", "You", "XL", "Recordings/Columbia", "Pop", "Cinematography", "VMA", "MTV", "VMAs", "Video", "Music", "Awards"], "subtitles": {}, "automatic_captions": {}, "duration": 285, "age_limit": 0, "annotations": null, "chapters": null, "webpage_url": "https://www.youtube.com/watch?v=hLQl3WQQoQ0", "view_count": 875185671, "like_count": 3575199, "dislike_count": 125654, "average_rating": 4.86418914795, "formats": [{"format_id": "249", "url": "https://r4---sn-i3beln76.googlevideo.com/videoplayback?clen=1914472&lmt=1449595680426838&dur=284.921&ipbits=0&pl=48&mv=m&ei=EfcfWeX6A8nc4gKA46bABQ&ms=au&source=youtube&mm=31&expire=1495288689&id=o-ABD1283AoGHfAeFudcBdvlxbCJPp57b58OY7SJxLSzJ7&itag=249&mn=sn-i3beln76&mt=1495266983&upn=rNM9qKuwTCA&signature=1D85E2817A22ED2599C22E776C14798D9E17333A.72CB50984B866EC2ECDF605D6A2479DC1EFFD945&sparams=clen%2Cdur%2Cei%2Cgir%2Cid%2Cinitcwndbps%2Cip%2Cipbits%2Citag%2Ckeepalive%2Clmt%2Cmime%2Cmm%2Cmn%2Cms%2Cmv%2Cpl%2Crequiressl%2Csource%2Cupn%2Cexpire&initcwndbps=1577500&keepalive=yes&requiressl=yes&ip=2001%3A250%3A209%3A2000%3Ad82c%3Abfbf%3A5f8f%3A1e95&mime=audio%2Fwebm&gir=yes&key=yt6&ratebypass=yes", "player_url": null, "ext": "webm", "format_note": "DASH audio", "acodec": "opus", "abr": 50, "filesize": 1914472, "tbr": 56.214, "vcodec": "none", "format": "249 - audio only (DASH audio)", "protocol": "https", "http_headers": {"User-Agent": "Mozilla/5.0 (X11; Linux x86_64; rv:10.0) Gecko/20150101 Firefox/47.0 (Chrome)", "Accept-Charset": "ISO-8859-1,utf-8;q=0.7,*;q=0.7", "Accept": "text/html,application/xhtml+xml,application/xml;q=0.9,*/*;q=0.8", "Accept-Encoding": "gzip, deflate", "Accept-Language": "en-us,en;q=0.5"}}, {"format_id": "250", "url": "https://r4---sn-i3beln76.googlevideo.com/videoplayback?clen=2676477&lmt=1449595679187275&dur=284.921&ipbits=0&pl=48&mv=m&ei=EfcfWeX6A8nc4gKA46bABQ&ms=au&source=youtube&mm=31&expire=1495288689&id=o-ABD1283AoGHfAeFudcBdvlxbCJPp57b58OY7SJxLSzJ7&itag=250&mn=sn-i3beln76&mt=1495266983&upn=rNM9qKuwTCA&signature=7691953908E6C1E30ED4B5EA73B0D7959F6630CE.21D9B9AB1BE924CFEC5499401023AB82AF0A52F5&sparams=clen%2Cdur%2Cei%2Cgir%2Cid%2Cinitcwndbps%2Cip%2Cipbits%2Citag%2Ckeepalive%2Clmt%2Cmime%2Cmm%2Cmn%2Cms%2Cmv%2Cpl%2Crequiressl%2Csource%2Cupn%2Cexpire&initcwndbps=1577500&keepalive=yes&requiressl=yes&ip=2001%3A250%3A209%3A2000%3Ad82c%3Abfbf%3A5f8f%3A1e95&mime=audio%2Fwebm&gir=yes&key=yt6&ratebypass=yes", "player_url": null, "ext": "webm", "format_note": "DASH audio", "acodec": "opus", "abr": 70, "filesize": 2676477, "tbr": 80.395, "vcodec": "none", "format": "250 - audio only (DASH audio)", "protocol": "https", "http_headers": {"User-Agent": "Mozilla/5.0 (X11; Linux x86_64; rv:10.0) Gecko/20150101 Firefox/47.0 (Chrome)", "Accept-Charset": "ISO-8859-1,utf-8;q=0.7,*;q=0.7", "Accept": "text/html,application/xhtml+xml,application/xml;q=0.9,*/*;q=0.8", "Accept-Encoding": "gzip, deflate", "Accept-Language": "en-us,en;q=0.5"}}, {"format_id": "140", "url": "https://r4---sn-i3beln76.googlevideo.com/videoplayback?clen=4526825&lmt=1458204719976239&dur=284.978&ipbits=0&pl=48&mv=m&ei=EfcfWeX6A8nc4gKA46bABQ&ms=au&source=youtube&mm=31&expire=1495288689&id=o-ABD1283AoGHfAeFudcBdvlxbCJPp57b58OY7SJxLSzJ7&itag=140&mn=sn-i3beln76&mt=1495266983&upn=rNM9qKuwTCA&signature=E20FEF3D6A1E0A2019D0E3B94B5FEBD1CE28F52E.4F50ECE0EF45DC8DA5A9ACB157B3C461A31C756B&sparams=clen%2Cdur%2Cei%2Cgir%2Cid%2Cinitcwndbps%2Cip%2Cipbits%2Citag%2Ckeepalive%2Clmt%2Cmime%2Cmm%2Cmn%2Cms%2Cmv%2Cpl%2Crequiressl%2Csource%2Cupn%2Cexpire&initcwndbps=1577500&keepalive=yes&requiressl=yes&ip=2001%3A250%3A209%3A2000%3Ad82c%3Abfbf%3A5f8f%3A1e95&mime=audio%2Fmp4&gir=yes&key=yt6&ratebypass=yes", "player_url": null, "ext": "m4a", "format_note": "DASH audio", "acodec": "mp4a.40.2", "abr": 128, "container": "m4a_dash", "filesize": 4526825, "tbr": 128.103, "vcodec": "none", "format": "140 - audio only (DASH audio)", "protocol": "https", "http_headers": {"User-Agent": "Mozilla/5.0 (X11; Linux x86_64; rv:10.0) Gecko/20150101 Firefox/47.0 (Chrome)", "Accept-Charset": "ISO-8859-1,utf-8;q=0.7,*;q=0.7", "Accept": "text/html,application/xhtml+xml,application/xml;q=0.9,*/*;q=0.8", "Accept-Encoding": "gzip, deflate", "Accept-Language": "en-us,en;q=0.5"}}, {"format_id": "171", "url": "https://r4---sn-i3beln76.googlevideo.com/videoplayback?clen=4255714&lmt=1449595735074022&dur=284.913&ipbits=0&pl=48&mv=m&ei=EfcfWeX6A8nc4gKA46bABQ&ms=au&source=youtube&mm=31&expire=1495288689&id=o-ABD1283AoGHfAeFudcBdvlxbCJPp57b58OY7SJxLSzJ7&itag=171&mn=sn-i3beln76&mt=1495266983&upn=rNM9qKuwTCA&signature=2EA3236E83B1D3850F5D7D907E4110DD519404F8.04E8DB0B475E682EFABF593C56ABE0744A64D0D5&sparams=clen%2Cdur%2Cei%2Cgir%2Cid%2Cinitcwndbps%2Cip%2Cipbits%2Citag%2Ckeepalive%2Clmt%2Cmime%2Cmm%2Cmn%2Cms%2Cmv%2Cpl%2Crequiressl%2Csource%2Cupn%2Cexpire&initcwndbps=1577500&keepalive=yes&requiressl=yes&ip=2001%3A250%3A209%3A2000%3Ad82c%3Abfbf%3A5f8f%3A1e95&mime=audio%2Fwebm&gir=yes&key=yt6&ratebypass=yes", "player_url": null, "ext": "webm", "acodec": "vorbis", "format_note": "DASH audio", "abr": 128, "filesize": 4255714, "tbr": 130.914, "vcodec": "none", "format": "171 - audio only (DASH audio)", "protocol": "https", "http_headers": {"User-Agent": "Mozilla/5.0 (X11; Linux x86_64; rv:10.0) Gecko/20150101 Firefox/47.0 (Chrome)", "Accept-Charset": "ISO-8859-1,utf-8;q=0.7,*;q=0.7", "Accept": "text/html,application/xhtml+xml,application/xml;q=0.9,*/*;q=0.8", "Accept-Encoding": "gzip, deflate", "Accept-Language": "en-us,en;q=0.5"}}, {"format_id": "251", "url": "https://r4---sn-i3beln76.googlevideo.com/videoplayback?clen=5171005&lmt=1449595765512122&dur=284.921&ipbits=0&pl=48&mv=m&ei=EfcfWeX6A8nc4gKA46bABQ&ms=au&source=youtube&mm=31&expire=1495288689&id=o-ABD1283AoGHfAeFudcBdvlxbCJPp57b58OY7SJxLSzJ7&itag=251&mn=sn-i3beln76&mt=1495266983&upn=rNM9qKuwTCA&signature=28081CED2A4053F3F4DCBD75A550B7139EC400C7.643058DDB83F32AEA7A710FF9D75B3E25DD83E25&sparams=clen%2Cdur%2Cei%2Cgir%2Cid%2Cinitcwndbps%2Cip%2Cipbits%2Citag%2Ckeepalive%2Clmt%2Cmime%2Cmm%2Cmn%2Cms%2Cmv%2Cpl%2Crequiressl%2Csource%2Cupn%2Cexpire&initcwndbps=1577500&keepalive=yes&requiressl=yes&ip=2001%3A250%3A209%3A2000%3Ad82c%3Abfbf%3A5f8f%3A1e95&mime=audio%2Fwebm&gir=yes&key=yt6&ratebypass=yes", "player_url": null, "ext": "webm", "format_note": "DASH audio", "acodec": "opus", "abr": 160, "filesize": 5171005, "tbr": 152.787, "vcodec": "none", "format": "251 - audio only (DASH audio)", "protocol": "https", "http_headers": {"User-Agent": "Mozilla/5.0 (X11; Linux x86_64; rv:10.0) Gecko/20150101 Firefox/47.0 (Chrome)", "Accept-Charset": "ISO-8859-1,utf-8;q=0.7,*;q=0.7", "Accept": "text/html,application/xhtml+xml,application/xml;q=0.9,*/*;q=0.8", "Accept-Encoding": "gzip, deflate", "Accept-Language": "en-us,en;q=0.5"}}, {"format_id": "278", "url": "https://r4---sn-i3beln76.googlevideo.com/videoplayback?clen=3245400&lmt=1449671761289853&dur=284.880&ipbits=0&pl=48&mv=m&ei=EfcfWeX6A8nc4gKA46bABQ&ms=au&source=youtube&mm=31&expire=1495288689&id=o-ABD1283AoGHfAeFudcBdvlxbCJPp57b58OY7SJxLSzJ7&itag=278&mn=sn-i3beln76&mt=1495266983&upn=rNM9qKuwTCA&signature=29205653046648C154AFACCAAB38EAD3D7C50527.85F505FA74CD1B37399DD43812C23CD89D47CFD0&sparams=clen%2Cdur%2Cei%2Cgir%2Cid%2Cinitcwndbps%2Cip%2Cipbits%2Citag%2Ckeepalive%2Clmt%2Cmime%2Cmm%2Cmn%2Cms%2Cmv%2Cpl%2Crequiressl%2Csource%2Cupn%2Cexpire&initcwndbps=1577500&keepalive=yes&requiressl=yes&ip=2001%3A250%3A209%3A2000%3Ad82c%3Abfbf%3A5f8f%3A1e95&mime=video%2Fwebm&gir=yes&key=yt6&ratebypass=yes", "player_url": null, "ext": "webm", "height": 144, "format_note": "144p", "container": "webm", "vcodec": "vp9", "filesize": 3245400, "tbr": 101.775, "width": 256, "fps": 13, "acodec": "none", "format": "278 - 256x144 (144p)", "protocol": "https", "http_headers": {"User-Agent": "Mozilla/5.0 (X11; Linux x86_64; rv:10.0) Gecko/20150101 Firefox/47.0 (Chrome)", "Accept-Charset": "ISO-8859-1,utf-8;q=0.7,*;q=0.7", "Accept": "text/html,application/xhtml+xml,application/xml;q=0.9,*/*;q=0.8", "Accept-Encoding": "gzip, deflate", "Accept-Language": "en-us,en;q=0.5"}}, {"format_id": "160", "url": "https://r4---sn-i3beln76.googlevideo.com/videoplayback?clen=3908579&lmt=1458207258249727&dur=284.920&ipbits=0&pl=48&mv=m&ei=EfcfWeX6A8nc4gKA46bABQ&ms=au&source=youtube&mm=31&expire=1495288689&id=o-ABD1283AoGHfAeFudcBdvlxbCJPp57b58OY7SJxLSzJ7&itag=160&mn=sn-i3beln76&mt=1495266983&upn=rNM9qKuwTCA&signature=387E8EF762A44F64C9A40C8DF88FB7FCCE0C4F64.8505EA9B4D292AE39C49CF2D466464234C817BE1&sparams=clen%2Cdur%2Cei%2Cgir%2Cid%2Cinitcwndbps%2Cip%2Cipbits%2Citag%2Ckeepalive%2Clmt%2Cmime%2Cmm%2Cmn%2Cms%2Cmv%2Cpl%2Crequiressl%2Csource%2Cupn%2Cexpire&initcwndbps=1577500&keepalive=yes&requiressl=yes&ip=2001%3A250%3A209%3A2000%3Ad82c%3Abfbf%3A5f8f%3A1e95&mime=video%2Fmp4&gir=yes&key=yt6&ratebypass=yes", "player_url": null, "ext": "mp4", "height": 144, "format_note": "144p", "vcodec": "avc1.4d400c", "filesize": 3908579, "tbr": 111.895, "width": 256, "fps": 25, "acodec": "none", "format": "160 - 256x144 (144p)", "protocol": "https", "http_headers": {"User-Agent": "Mozilla/5.0 (X11; Linux x86_64; rv:10.0) Gecko/20150101 Firefox/47.0 (Chrome)", "Accept-Charset": "ISO-8859-1,utf-8;q=0.7,*;q=0.7", "Accept": "text/html,application/xhtml+xml,application/xml;q=0.9,*/*;q=0.8", "Accept-Encoding": "gzip, deflate", "Accept-Language": "en-us,en;q=0.5"}}, {"format_id": "242", "url": "https://r4---sn-i3beln76.googlevideo.com/videoplayback?clen=3908540&lmt=1449671761286414&dur=284.880&ipbits=0&pl=48&mv=m&ei=EfcfWeX6A8nc4gKA46bABQ&ms=au&source=youtube&mm=31&expire=1495288689&id=o-ABD1283AoGHfAeFudcBdvlxbCJPp57b58OY7SJxLSzJ7&itag=242&mn=sn-i3beln76&mt=1495266983&upn=rNM9qKuwTCA&signature=768D179D4DEEC5EC05EB2F4BAC7153BFAFFC790A.088074C6ED795666DAC7B5F23069FE3D0386FED9&sparams=clen%2Cdur%2Cei%2Cgir%2Cid%2Cinitcwndbps%2Cip%2Cipbits%2Citag%2Ckeepalive%2Clmt%2Cmime%2Cmm%2Cmn%2Cms%2Cmv%2Cpl%2Crequiressl%2Csource%2Cupn%2Cexpire&initcwndbps=1577500&keepalive=yes&requiressl=yes&ip=2001%3A250%3A209%3A2000%3Ad82c%3Abfbf%3A5f8f%3A1e95&mime=video%2Fwebm&gir=yes&key=yt6&ratebypass=yes", "player_url": null, "ext": "webm", "height": 240, "format_note": "240p", "vcodec": "vp9", "filesize": 3908540, "tbr": 185.778, "width": 426, "fps": 25, "acodec": "none", "format": "242 - 426x240 (240p)", "protocol": "https", "http_headers": {"User-Agent": "Mozilla/5.0 (X11; Linux x86_64; rv:10.0) Gecko/20150101 Firefox/47.0 (Chrome)", "Accept-Charset": "ISO-8859-1,utf-8;q=0.7,*;q=0.7", "Accept": "text/html,application/xhtml+xml,application/xml;q=0.9,*/*;q=0.8", "Accept-Encoding": "gzip, deflate", "Accept-Language": "en-us,en;q=0.5"}}, {"format_id": "133", "url": "https://r4---sn-i3beln76.googlevideo.com/videoplayback?clen=8766397&lmt=1458207258356288&dur=284.920&ipbits=0&pl=48&mv=m&ei=EfcfWeX6A8nc4gKA46bABQ&ms=au&source=youtube&mm=31&expire=1495288689&id=o-ABD1283AoGHfAeFudcBdvlxbCJPp57b58OY7SJxLSzJ7&itag=133&mn=sn-i3beln76&mt=1495266983&upn=rNM9qKuwTCA&signature=D6A09D2E23AA074362C26E84704D515E87347ECC.4E01B349D20CF68F43A5AE435E6BD7A4D9F40D95&sparams=clen%2Cdur%2Cei%2Cgir%2Cid%2Cinitcwndbps%2Cip%2Cipbits%2Citag%2Ckeepalive%2Clmt%2Cmime%2Cmm%2Cmn%2Cms%2Cmv%2Cpl%2Crequiressl%2Csource%2Cupn%2Cexpire&initcwndbps=1577500&keepalive=yes&requiressl=yes&ip=2001%3A250%3A209%3A2000%3Ad82c%3Abfbf%3A5f8f%3A1e95&mime=video%2Fmp4&gir=yes&key=yt6&ratebypass=yes", "player_url": null, "ext": "mp4", "height": 240, "format_note": "240p", "vcodec": "avc1.4d4015", "filesize": 8766397, "tbr": 253.526, "width": 426, "fps": 25, "acodec": "none", "format": "133 - 426x240 (240p)", "protocol": "https", "http_headers": {"User-Agent": "Mozilla/5.0 (X11; Linux x86_64; rv:10.0) Gecko/20150101 Firefox/47.0 (Chrome)", "Accept-Charset": "ISO-8859-1,utf-8;q=0.7,*;q=0.7", "Accept": "text/html,application/xhtml+xml,application/xml;q=0.9,*/*;q=0.8", "Accept-Encoding": "gzip, deflate", "Accept-Language": "en-us,en;q=0.5"}}, {"format_id": "134", "url": "https://r4---sn-i3beln76.googlevideo.com/videoplayback?clen=8534708&lmt=1458207258321145&dur=284.920&ipbits=0&pl=48&mv=m&ei=EfcfWeX6A8nc4gKA46bABQ&ms=au&source=youtube&mm=31&expire=1495288689&id=o-ABD1283AoGHfAeFudcBdvlxbCJPp57b58OY7SJxLSzJ7&itag=134&mn=sn-i3beln76&mt=1495266983&upn=rNM9qKuwTCA&signature=254A8F72968DEDC35130972C71319D8DB32EE40E.0630CE3E251F79A22C41362B9023BE20BDE78030&sparams=clen%2Cdur%2Cei%2Cgir%2Cid%2Cinitcwndbps%2Cip%2Cipbits%2Citag%2Ckeepalive%2Clmt%2Cmime%2Cmm%2Cmn%2Cms%2Cmv%2Cpl%2Crequiressl%2Csource%2Cupn%2Cexpire&initcwndbps=1577500&keepalive=yes&requiressl=yes&ip=2001%3A250%3A209%3A2000%3Ad82c%3Abfbf%3A5f8f%3A1e95&mime=video%2Fmp4&gir=yes&key=yt6&ratebypass=yes", "player_url": null, "ext": "mp4", "height": 360, "format_note": "360p", "vcodec": "avc1.4d401e", "filesize": 8534708, "tbr": 285.326, "width": 640, "fps": 25, "acodec": "none", "format": "134 - 640x360 (360p)", "protocol": "https", "http_headers": {"User-Agent": "Mozilla/5.0 (X11; Linux x86_64; rv:10.0) Gecko/20150101 Firefox/47.0 (Chrome)", "Accept-Charset": "ISO-8859-1,utf-8;q=0.7,*;q=0.7", "Accept": "text/html,application/xhtml+xml,application/xml;q=0.9,*/*;q=0.8", "Accept-Encoding": "gzip, deflate", "Accept-Language": "en-us,en;q=0.5"}}, {"format_id": "243", "url": "https://r4---sn-i3beln76.googlevideo.com/videoplayback?clen=6757850&lmt=1449671761925592&dur=284.880&ipbits=0&pl=48&mv=m&ei=EfcfWeX6A8nc4gKA46bABQ&ms=au&source=youtube&mm=31&expire=1495288689&id=o-ABD1283AoGHfAeFudcBdvlxbCJPp57b58OY7SJxLSzJ7&itag=243&mn=sn-i3beln76&mt=1495266983&upn=rNM9qKuwTCA&signature=7FC29BFB17B8375D938CBC48D304420FDFA53DF7.E0BBB96C402623F832797094C6A4F7C5569BD498&sparams=clen%2Cdur%2Cei%2Cgir%2Cid%2Cinitcwndbps%2Cip%2Cipbits%2Citag%2Ckeepalive%2Clmt%2Cmime%2Cmm%2Cmn%2Cms%2Cmv%2Cpl%2Crequiressl%2Csource%2Cupn%2Cexpire&initcwndbps=1577500&keepalive=yes&requiressl=yes&ip=2001%3A250%3A209%3A2000%3Ad82c%3Abfbf%3A5f8f%3A1e95&mime=video%2Fwebm&gir=yes&key=yt6&ratebypass=yes", "player_url": null, "ext": "webm", "height": 360, "format_note": "360p", "vcodec": "vp9", "filesize": 6757850, "tbr": 323.96, "width": 640, "fps": 25, "acodec": "none", "format": "243 - 640x360 (360p)", "protocol": "https", "http_headers": {"User-Agent": "Mozilla/5.0 (X11; Linux x86_64; rv:10.0) Gecko/20150101 Firefox/47.0 (Chrome)", "Accept-Charset": "ISO-8859-1,utf-8;q=0.7,*;q=0.7", "Accept": "text/html,application/xhtml+xml,application/xml;q=0.9,*/*;q=0.8", "Accept-Encoding": "gzip, deflate", "Accept-Language": "en-us,en;q=0.5"}}, {"format_id": "244", "url": "https://r4---sn-i3beln76.googlevideo.com/videoplayback?clen=11969551&lmt=1449671761415474&dur=284.880&ipbits=0&pl=48&mv=m&ei=EfcfWeX6A8nc4gKA46bABQ&ms=au&source=youtube&mm=31&expire=1495288689&id=o-ABD1283AoGHfAeFudcBdvlxbCJPp57b58OY7SJxLSzJ7&itag=244&mn=sn-i3beln76&mt=1495266983&upn=rNM9qKuwTCA&signature=833ECA092C66C012DEEA26EC2D121D713337E5A6.DA3CF8E181CFF9CD8E4327E41556016C2BFE2DFB&sparams=clen%2Cdur%2Cei%2Cgir%2Cid%2Cinitcwndbps%2Cip%2Cipbits%2Citag%2Ckeepalive%2Clmt%2Cmime%2Cmm%2Cmn%2Cms%2Cmv%2Cpl%2Crequiressl%2Csource%2Cupn%2Cexpire&initcwndbps=1577500&keepalive=yes&requiressl=yes&ip=2001%3A250%3A209%3A2000%3Ad82c%3Abfbf%3A5f8f%3A1e95&mime=video%2Fwebm&gir=yes&key=yt6&ratebypass=yes", "player_url": null, "ext": "webm", "height": 480, "format_note": "480p", "vcodec": "vp9", "filesize": 11969551, "tbr": 683.97, "width": 854, "fps": 25, "acodec": "none", "format": "244 - 854x480 (480p)", "protocol": "https", "http_headers": {"User-Agent": "Mozilla/5.0 (X11; Linux x86_64; rv:10.0) Gecko/20150101 Firefox/47.0 (Chrome)", "Accept-Charset": "ISO-8859-1,utf-8;q=0.7,*;q=0.7", "Accept": "text/html,application/xhtml+xml,application/xml;q=0.9,*/*;q=0.8", "Accept-Encoding": "gzip, deflate", "Accept-Language": "en-us,en;q=0.5"}}, {"format_id": "135", "url": "https://r4---sn-i3beln76.googlevideo.com/videoplayback?clen=18306556&lmt=1458207258774851&dur=284.920&ipbits=0&pl=48&mv=m&ei=EfcfWeX6A8nc4gKA46bABQ&ms=au&source=youtube&mm=31&expire=1495288689&id=o-ABD1283AoGHfAeFudcBdvlxbCJPp57b58OY7SJxLSzJ7&itag=135&mn=sn-i3beln76&mt=1495266983&upn=rNM9qKuwTCA&signature=94A18124071AB39113654BD4E91B32036433E9FC.876648F6C8B8C1219E826017F8709A198FD7087F&sparams=clen%2Cdur%2Cei%2Cgir%2Cid%2Cinitcwndbps%2Cip%2Cipbits%2Citag%2Ckeepalive%2Clmt%2Cmime%2Cmm%2Cmn%2Cms%2Cmv%2Cpl%2Crequiressl%2Csource%2Cupn%2Cexpire&initcwndbps=1577500&keepalive=yes&requiressl=yes&ip=2001%3A250%3A209%3A2000%3Ad82c%3Abfbf%3A5f8f%3A1e95&mime=video%2Fmp4&gir=yes&key=yt6&ratebypass=yes", "player_url": null, "ext": "mp4", "height": 480, "format_note": "480p", "vcodec": "avc1.4d401e", "filesize": 18306556, "tbr": 711.167, "width": 854, "fps": 25, "acodec": "none", "format": "135 - 854x480 (480p)", "protocol": "https", "http_headers": {"User-Agent": "Mozilla/5.0 (X11; Linux x86_64; rv:10.0) Gecko/20150101 Firefox/47.0 (Chrome)", "Accept-Charset": "ISO-8859-1,utf-8;q=0.7,*;q=0.7", "Accept": "text/html,application/xhtml+xml,application/xml;q=0.9,*/*;q=0.8", "Accept-Encoding": "gzip, deflate", "Accept-Language": "en-us,en;q=0.5"}}, {"format_id": "247", "url": "https://r4---sn-i3beln76.googlevideo.com/videoplayback?clen=32109343&lmt=1449671762550111&dur=284.880&ipbits=0&pl=48&mv=m&ei=EfcfWeX6A8nc4gKA46bABQ&ms=au&source=youtube&mm=31&expire=1495288689&id=o-ABD1283AoGHfAeFudcBdvlxbCJPp57b58OY7SJxLSzJ7&itag=247&mn=sn-i3beln76&mt=1495266983&upn=rNM9qKuwTCA&signature=5539D132B0A21EF7A5760186B006253EF5C42B85.3DD25F6334CBC4E2F7A47F8B585CB3C89B690628&sparams=clen%2Cdur%2Cei%2Cgir%2Cid%2Cinitcwndbps%2Cip%2Cipbits%2Citag%2Ckeepalive%2Clmt%2Cmime%2Cmm%2Cmn%2Cms%2Cmv%2Cpl%2Crequiressl%2Csource%2Cupn%2Cexpire&initcwndbps=1577500&keepalive=yes&requiressl=yes&ip=2001%3A250%3A209%3A2000%3Ad82c%3Abfbf%3A5f8f%3A1e95&mime=video%2Fwebm&gir=yes&key=yt6&ratebypass=yes", "player_url": null, "ext": "webm", "height": 720, "format_note": "720p", "vcodec": "vp9", "filesize": 32109343, "tbr": 1777.376, "width": 1280, "fps": 25, "acodec": "none", "format": "247 - 1280x720 (720p)", "protocol": "https", "http_headers": {"User-Agent": "Mozilla/5.0 (X11; Linux x86_64; rv:10.0) Gecko/20150101 Firefox/47.0 (Chrome)", "Accept-Charset": "ISO-8859-1,utf-8;q=0.7,*;q=0.7", "Accept": "text/html,application/xhtml+xml,application/xml;q=0.9,*/*;q=0.8", "Accept-Encoding": "gzip, deflate", "Accept-Language": "en-us,en;q=0.5"}}, {"format_id": "136", "url": "https://r4---sn-i3beln76.googlevideo.com/videoplayback?clen=39316179&lmt=1458207260235393&dur=284.920&ipbits=0&pl=48&mv=m&ei=EfcfWeX6A8nc4gKA46bABQ&ms=au&source=youtube&mm=31&expire=1495288689&id=o-ABD1283AoGHfAeFudcBdvlxbCJPp57b58OY7SJxLSzJ7&itag=136&mn=sn-i3beln76&mt=1495266983&upn=rNM9qKuwTCA&signature=BCCFC0CC9AAE6C000EA8CC48410131D7411110B0.07BF5E464D60C7845624A2D2B1B9ED33CC99AE22&sparams=clen%2Cdur%2Cei%2Cgir%2Cid%2Cinitcwndbps%2Cip%2Cipbits%2Citag%2Ckeepalive%2Clmt%2Cmime%2Cmm%2Cmn%2Cms%2Cmv%2Cpl%2Crequiressl%2Csource%2Cupn%2Cexpire&initcwndbps=1577500&keepalive=yes&requiressl=yes&ip=2001%3A250%3A209%3A2000%3Ad82c%3Abfbf%3A5f8f%3A1e95&mime=video%2Fmp4&gir=yes&key=yt6&ratebypass=yes", "player_url": null, "ext": "mp4", "height": 720, "format_note": "720p", "vcodec": "avc1.4d401f", "filesize": 39316179, "tbr": 1899.492, "width": 1280, "fps": 25, "acodec": "none", "format": "136 - 1280x720 (720p)", "protocol": "https", "http_headers": {"User-Agent": "Mozilla/5.0 (X11; Linux x86_64; rv:10.0) Gecko/20150101 Firefox/47.0 (Chrome)", "Accept-Charset": "ISO-8859-1,utf-8;q=0.7,*;q=0.7", "Accept": "text/html,application/xhtml+xml,application/xml;q=0.9,*/*;q=0.8", "Accept-Encoding": "gzip, deflate", "Accept-Language": "en-us,en;q=0.5"}}, {"format_id": "248", "url": "https://r4---sn-i3beln76.googlevideo.com/videoplayback?clen=73740232&lmt=1449596331403135&dur=284.880&ipbits=0&pl=48&mv=m&ei=EfcfWeX6A8nc4gKA46bABQ&ms=au&source=youtube&mm=31&expire=1495288689&id=o-ABD1283AoGHfAeFudcBdvlxbCJPp57b58OY7SJxLSzJ7&itag=248&mn=sn-i3beln76&mt=1495266983&upn=rNM9qKuwTCA&signature=42F3C964495C491E5F44BE3690BA9D8299B6876B.980A09E3AFEA993FB57699DF92F377729531D4D0&sparams=clen%2Cdur%2Cei%2Cgir%2Cid%2Cinitcwndbps%2Cip%2Cipbits%2Citag%2Ckeepalive%2Clmt%2Cmime%2Cmm%2Cmn%2Cms%2Cmv%2Cpl%2Crequiressl%2Csource%2Cupn%2Cexpire&initcwndbps=1577500&keepalive=yes&requiressl=yes&ip=2001%3A250%3A209%3A2000%3Ad82c%3Abfbf%3A5f8f%3A1e95&mime=video%2Fwebm&gir=yes&key=yt6&ratebypass=yes", "player_url": null, "ext": "webm", "height": 1080, "format_note": "1080p", "vcodec": "vp9", "filesize": 73740232, "tbr": 3212.939, "width": 1920, "fps": 25, "acodec": "none", "format": "248 - 1920x1080 (1080p)", "protocol": "https", "http_headers": {"User-Agent": "Mozilla/5.0 (X11; Linux x86_64; rv:10.0) Gecko/20150101 Firefox/47.0 (Chrome)", "Accept-Charset": "ISO-8859-1,utf-8;q=0.7,*;q=0.7", "Accept": "text/html,application/xhtml+xml,application/xml;q=0.9,*/*;q=0.8", "Accept-Encoding": "gzip, deflate", "Accept-Language": "en-us,en;q=0.5"}}, {"format_id": "137", "url": "https://r4---sn-i3beln76.googlevideo.com/videoplayback?clen=81189187&lmt=1458205362759400&dur=284.920&ipbits=0&pl=48&mv=m&ei=EfcfWeX6A8nc4gKA46bABQ&ms=au&source=youtube&mm=31&expire=1495288689&id=o-ABD1283AoGHfAeFudcBdvlxbCJPp57b58OY7SJxLSzJ7&itag=137&mn=sn-i3beln76&mt=1495266983&upn=rNM9qKuwTCA&signature=50733CFDFA7872A00B87CAA3985262369F1D4D2F.18F2C4DB36E36C63EE478EA3143996371E98FB16&sparams=clen%2Cdur%2Cei%2Cgir%2Cid%2Cinitcwndbps%2Cip%2Cipbits%2Citag%2Ckeepalive%2Clmt%2Cmime%2Cmm%2Cmn%2Cms%2Cmv%2Cpl%2Crequiressl%2Csource%2Cupn%2Cexpire&initcwndbps=1577500&keepalive=yes&requiressl=yes&ip=2001%3A250%3A209%3A2000%3Ad82c%3Abfbf%3A5f8f%3A1e95&mime=video%2Fmp4&gir=yes&key=yt6&ratebypass=yes", "player_url": null, "ext": "mp4", "height": 1080, "format_note": "1080p", "vcodec": "avc1.640028", "filesize": 81189187, "tbr": 4418.387, "width": 1920, "fps": 25, "acodec": "none", "format": "137 - 1920x1080 (1080p)", "protocol": "https", "http_headers": {"User-Agent": "Mozilla/5.0 (X11; Linux x86_64; rv:10.0) Gecko/20150101 Firefox/47.0 (Chrome)", "Accept-Charset": "ISO-8859-1,utf-8;q=0.7,*;q=0.7", "Accept": "text/html,application/xhtml+xml,application/xml;q=0.9,*/*;q=0.8", "Accept-Encoding": "gzip, deflate", "Accept-Language": "en-us,en;q=0.5"}}, {"format_id": "17", "url": "https://r4---sn-i3beln76.googlevideo.com/videoplayback?clen=2918297&lmt=1394276569379128&dur=285.326&ipbits=0&pl=48&mv=m&ei=EfcfWeX6A8nc4gKA46bABQ&ms=au&source=youtube&mm=31&expire=1495288689&id=o-ABD1283AoGHfAeFudcBdvlxbCJPp57b58OY7SJxLSzJ7&itag=17&mt=1495266983&upn=rNM9qKuwTCA&signature=7111D00AB524C2C2A6976BDD22C73CA223BFF70A.D8F996791D8E5B0B7A506DB3A2089F990C88A15F&sparams=clen%2Cdur%2Cei%2Cgir%2Cid%2Cinitcwndbps%2Cip%2Cipbits%2Citag%2Clmt%2Cmime%2Cmm%2Cmn%2Cms%2Cmv%2Cpl%2Crequiressl%2Csource%2Cupn%2Cexpire&initcwndbps=1577500&mn=sn-i3beln76&requiressl=yes&ip=2001%3A250%3A209%3A2000%3Ad82c%3Abfbf%3A5f8f%3A1e95&mime=video%2F3gpp&gir=yes&key=yt6&ratebypass=yes", "player_url": null, "ext": "3gp", "width": 176, "height": 144, "acodec": "mp4a.40.2", "abr": 24, "vcodec": "mp4v.20.3", "resolution": "176x144", "format_note": "small", "format": "17 - 176x144 (small)", "protocol": "https", "http_headers": {"User-Agent": "Mozilla/5.0 (X11; Linux x86_64; rv:10.0) Gecko/20150101 Firefox/47.0 (Chrome)", "Accept-Charset": "ISO-8859-1,utf-8;q=0.7,*;q=0.7", "Accept": "text/html,application/xhtml+xml,application/xml;q=0.9,*/*;q=0.8", "Accept-Encoding": "gzip, deflate", "Accept-Language": "en-us,en;q=0.5"}}, {"format_id": "36", "url": "https://r4---sn-i3beln76.googlevideo.com/videoplayback?clen=8058585&lmt=1427537128530943&dur=285.094&ipbits=0&pl=48&mv=m&ei=EfcfWeX6A8nc4gKA46bABQ&ms=au&source=youtube&mm=31&expire=1495288689&id=o-ABD1283AoGHfAeFudcBdvlxbCJPp57b58OY7SJxLSzJ7&itag=36&mt=1495266983&upn=rNM9qKuwTCA&signature=83B1AD67C2CB716E681D3B1D94459ACCE02FCB59.6020E9FAFE5A5A90B9C1E2A06E4A2722DDE0E4A5&sparams=clen%2Cdur%2Cei%2Cgir%2Cid%2Cinitcwndbps%2Cip%2Cipbits%2Citag%2Clmt%2Cmime%2Cmm%2Cmn%2Cms%2Cmv%2Cpl%2Crequiressl%2Csource%2Cupn%2Cexpire&initcwndbps=1577500&mn=sn-i3beln76&requiressl=yes&ip=2001%3A250%3A209%3A2000%3Ad82c%3Abfbf%3A5f8f%3A1e95&mime=video%2F3gpp&gir=yes&key=yt6&ratebypass=yes", "player_url": null, "ext": "3gp", "width": 320, "acodec": "mp4a.40.2", "vcodec": "mp4v.20.3", "resolution": "320x180", "height": 180, "format_note": "small", "format": "36 - 320x180 (small)", "protocol": "https", "http_headers": {"User-Agent": "Mozilla/5.0 (X11; Linux x86_64; rv:10.0) Gecko/20150101 Firefox/47.0 (Chrome)", "Accept-Charset": "ISO-8859-1,utf-8;q=0.7,*;q=0.7", "Accept": "text/html,application/xhtml+xml,application/xml;q=0.9,*/*;q=0.8", "Accept-Encoding": "gzip, deflate", "Accept-Language": "en-us,en;q=0.5"}}, {"format_id": "43", "url": "https://r4---sn-i3beln76.googlevideo.com/videoplayback?clen=19512034&ratebypass=yes&lmt=1317162071536783&dur=0.000&ipbits=0&pl=48&mv=m&ei=EfcfWeX6A8nc4gKA46bABQ&ms=au&source=youtube&mm=31&expire=1495288689&id=o-ABD1283AoGHfAeFudcBdvlxbCJPp57b58OY7SJxLSzJ7&itag=43&mt=1495266983&upn=rNM9qKuwTCA&signature=8B1FF92D5E50C92B61F642714931D33F35D5E988.D621B64638E9BD97DEF0D64259F093DAA368B195&sparams=clen%2Cdur%2Cei%2Cgir%2Cid%2Cinitcwndbps%2Cip%2Cipbits%2Citag%2Clmt%2Cmime%2Cmm%2Cmn%2Cms%2Cmv%2Cpl%2Cratebypass%2Crequiressl%2Csource%2Cupn%2Cexpire&initcwndbps=1577500&mn=sn-i3beln76&requiressl=yes&ip=2001%3A250%3A209%3A2000%3Ad82c%3Abfbf%3A5f8f%3A1e95&mime=video%2Fwebm&gir=yes&key=yt6", "player_url": null, "ext": "webm", "width": 640, "height": 360, "acodec": "vorbis", "abr": 128, "vcodec": "vp8.0", "resolution": "640x360", "format_note": "medium", "format": "43 - 640x360 (medium)", "protocol": "https", "http_headers": {"User-Agent": "Mozilla/5.0 (X11; Linux x86_64; rv:10.0) Gecko/20150101 Firefox/47.0 (Chrome)", "Accept-Charset": "ISO-8859-1,utf-8;q=0.7,*;q=0.7", "Accept": "text/html,application/xhtml+xml,application/xml;q=0.9,*/*;q=0.8", "Accept-Encoding": "gzip, deflate", "Accept-Language": "en-us,en;q=0.5"}}, {"format_id": "18", "url": "https://r4---sn-i3beln76.googlevideo.com/videoplayback?clen=13714021&ratebypass=yes&lmt=1458204883357312&dur=284.978&ipbits=0&pl=48&mv=m&ei=EfcfWeX6A8nc4gKA46bABQ&ms=au&source=youtube&mm=31&expire=1495288689&id=o-ABD1283AoGHfAeFudcBdvlxbCJPp57b58OY7SJxLSzJ7&itag=18&mt=1495266983&upn=rNM9qKuwTCA&signature=CE3EF40915C12C2BC87A2234335DD7A56426448D.64CB15E9B78836D77A09FCEDAD0E9FFBCC58A3A5&sparams=clen%2Cdur%2Cei%2Cgir%2Cid%2Cinitcwndbps%2Cip%2Cipbits%2Citag%2Clmt%2Cmime%2Cmm%2Cmn%2Cms%2Cmv%2Cpl%2Cratebypass%2Crequiressl%2Csource%2Cupn%2Cexpire&initcwndbps=1577500&mn=sn-i3beln76&requiressl=yes&ip=2001%3A250%3A209%3A2000%3Ad82c%3Abfbf%3A5f8f%3A1e95&mime=video%2Fmp4&gir=yes&key=yt6", "player_url": null, "ext": "mp4", "width": 640, "height": 360, "acodec": "mp4a.40.2", "abr": 96, "vcodec": "avc1.42001E", "resolution": "640x360", "format_note": "medium", "format": "18 - 640x360 (medium)", "protocol": "https", "http_headers": {"User-Agent": "Mozilla/5.0 (X11; Linux x86_64; rv:10.0) Gecko/20150101 Firefox/47.0 (Chrome)", "Accept-Charset": "ISO-8859-1,utf-8;q=0.7,*;q=0.7", "Accept": "text/html,application/xhtml+xml,application/xml;q=0.9,*/*;q=0.8", "Accept-Encoding": "gzip, deflate", "Accept-Language": "en-us,en;q=0.5"}}, {"format_id": "22", "url": "https://r4---sn-i3beln76.googlevideo.com/videoplayback?ratebypass=yes&lmt=1472152687260929&dur=284.978&ipbits=0&pl=48&mv=m&ei=EfcfWeX6A8nc4gKA46bABQ&ms=au&source=youtube&mm=31&expire=1495288689&id=o-ABD1283AoGHfAeFudcBdvlxbCJPp57b58OY7SJxLSzJ7&itag=22&mt=1495266983&upn=rNM9qKuwTCA&signature=A3D5752FEFBFC63A3C2838081245F12A830887C2.BFA5D985070ED3E4970F873FD15938DA3DE74636&sparams=dur%2Cei%2Cid%2Cinitcwndbps%2Cip%2Cipbits%2Citag%2Clmt%2Cmime%2Cmm%2Cmn%2Cms%2Cmv%2Cpl%2Cratebypass%2Crequiressl%2Csource%2Cupn%2Cexpire&initcwndbps=1577500&mn=sn-i3beln76&requiressl=yes&ip=2001%3A250%3A209%3A2000%3Ad82c%3Abfbf%3A5f8f%3A1e95&mime=video%2Fmp4&key=yt6", "player_url": null, "ext": "mp4", "width": 1280, "height": 720, "acodec": "mp4a.40.2", "abr": 192, "vcodec": "avc1.64001F", "resolution": "1280x720", "format_note": "hd720", "format": "22 - 1280x720 (hd720)", "protocol": "https", "http_headers": {"User-Agent": "Mozilla/5.0 (X11; Linux x86_64; rv:10.0) Gecko/20150101 Firefox/47.0 (Chrome)", "Accept-Charset": "ISO-8859-1,utf-8;q=0.7,*;q=0.7", "Accept": "text/html,application/xhtml+xml,application/xml;q=0.9,*/*;q=0.8", "Accept-Encoding": "gzip, deflate", "Accept-Language": "en-us,en;q=0.5"}}], "is_live": null, "start_time": null, "end_time": null, "series": null, "season_number": null, "episode_number": null, "extractor": "youtube", "webpage_url_basename": "hLQl3WQQoQ0", "extractor_key": "Youtube", "n_entries": 100, "playlist": "most viewed music videos on YouTube.", "playlist_id": "PL8A83124F1D79BD4F", "playlist_title": "most viewed music videos on YouTube.", "playlist_index": 53, "thumbnails": [{"url": "https://i.ytimg.com/vi/hLQl3WQQoQ0/maxresdefault.jpg", "id": "0"}], "display_id": "hLQl3WQQoQ0", "format_id": "22", "url": "https://r4---sn-i3beln76.googlevideo.com/videoplayback?ratebypass=yes&lmt=1472152687260929&dur=284.978&ipbits=0&pl=48&mv=m&ei=EfcfWeX6A8nc4gKA46bABQ&ms=au&source=youtube&mm=31&expire=1495288689&id=o-ABD1283AoGHfAeFudcBdvlxbCJPp57b58OY7SJxLSzJ7&itag=22&mt=1495266983&upn=rNM9qKuwTCA&signature=A3D5752FEFBFC63A3C2838081245F12A830887C2.BFA5D985070ED3E4970F873FD15938DA3DE74636&sparams=dur%2Cei%2Cid%2Cinitcwndbps%2Cip%2Cipbits%2Citag%2Clmt%2Cmime%2Cmm%2Cmn%2Cms%2Cmv%2Cpl%2Cratebypass%2Crequiressl%2Csource%2Cupn%2Cexpire&initcwndbps=1577500&mn=sn-i3beln76&requiressl=yes&ip=2001%3A250%3A209%3A2000%3Ad82c%3Abfbf%3A5f8f%3A1e95&mime=video%2Fmp4&key=yt6", "player_url": null, "ext": "mp4", "width": 1280, "height": 720, "acodec": "mp4a.40.2", "abr": 192, "vcodec": "avc1.64001F", "resolution": "1280x720", "format_note": "hd720", "format": "22 - 1280x720 (hd720)", "protocol": "https", "http_headers": {"User-Agent": "Mozilla/5.0 (X11; Linux x86_64; rv:10.0) Gecko/20150101 Firefox/47.0 (Chrome)", "Accept-Charset": "ISO-8859-1,utf-8;q=0.7,*;q=0.7", "Accept": "text/html,application/xhtml+xml,application/xml;q=0.9,*/*;q=0.8", "Accept-Encoding": "gzip, deflate", "Accept-Language": "en-us,en;q=0.5"}, "fulltitle": "Adele - Someone Like You", "_filename": "Adele - Someone Like You-hLQl3WQQoQ0.mp4"}