{"id": "0HDdjwpPM3Y", "uploader": "JessieJVEVO", "uploader_id": "JessieJVEVO", "uploader_url": "http://www.youtube.com/user/JessieJVEVO", "upload_date": "20140825", "license": "Standard YouTube License", "creator": null, "title": "Jessie J, Ariana Grande, Nicki Minaj - Bang Bang ft. Ariana Grande, Nicki Minaj", "alt_title": null, "thumbnail": "https://i.ytimg.com/vi/0HDdjwpPM3Y/maxresdefault.jpg", "description": "Get Jessie J + Ariana Grande + Nicki Minaj \"Bang Bang\" now! http://smarturl.it/JSJSweetTalkerdlxDA", "categories": ["Music"], "tags": ["Jessie J", "Ariana Grande", "Nicki Minaj", "Bang Bang", "Jessie", "Ariana", "Grande", "Nicki", "Minaj", "Bang", "jessie j who you are", "jessie j live", "jessie j price tag", "jessie j songs", "jessie j bang bang", "bang bang song", "bang bang lyrics", "bang bang lyric video", "bang bang ariana grande", "bang bang nicki minaj", "bang bang rap lyrics", "sweet talker jessie j lyrics", "sweet talker lyrics", "sweet talker album", "sweet talker", "sweet talker jessie j"], "subtitles": {}, "automatic_captions": {}, "duration": 262, "age_limit": 0, "annotations": null, "chapters": null, "webpage_url": "https://www.youtube.com/watch?v=0HDdjwpPM3Y", "view_count": 910182393, "like_count": 3537447, "dislike_count": 200004, "average_rating": 4.78594589233, "formats": [{"format_id": "249", "url": "https://r2---sn-i3beln7s.googlevideo.com/videoplayback?ipbits=0&initcwndbps=1576250&expire=1495288645&upn=l1KXqkv-hzg&mime=audio%2Fwebm&id=o-AANfbbWDU6ST1z8qBYgYMM8w_38v_S7qhFT12LJfzFBo&dur=262.061&source=youtube&keepalive=yes&ip=2001%3A250%3A209%3A2000%3Ad82c%3Abfbf%3A5f8f%3A1e95&requiressl=yes&lmt=1449650106403986&itag=249&ei=5PYfWeilPIbe4gLX4KjIBw&ms=au&mt=1495266922&pl=48&mv=m&clen=1631585&signature=59CB57EE2A87710E1668BD3332398A8842E2E06C.603AA99DB0316E6FA22ECA419E08A3EA2CC9EDA8&key=yt6&mm=31&mn=sn-i3beln7s&gir=yes&sparams=clen%2Cdur%2Cei%2Cgir%2Cid%2Cinitcwndbps%2Cip%2Cipbits%2Citag%2Ckeepalive%2Clmt%2Cmime%2Cmm%2Cmn%2Cms%2Cmv%2Cpl%2Crequiressl%2Csource%2Cupn%2Cexpire&ratebypass=yes", "player_url": null, "ext": "webm", "format_note": "DASH audio", "acodec": "opus", "abr": 50, "filesize": 1631585, "tbr": 56.773, "vcodec": "none", "format": "249 - audio only (DASH audio)", "protocol": "https", "http_headers": {"User-Agent": "Mozilla/5.0 (X11; Linux x86_64; rv:10.0) Gecko/20150101 Firefox/47.0 (Chrome)", "Accept-Charset": "ISO-8859-1,utf-8;q=0.7,*;q=0.7", "Accept": "text/html,application/xhtml+xml,application/xml;q=0.9,*/*;q=0.8", "Accept-Encoding": "gzip, deflate", "Accept-Language": "en-us,en;q=0.5"}}, {"format_id": "250", "url": "https://r2---sn-i3beln7s.googlevideo.com/videoplayback?ipbits=0&initcwndbps=1576250&expire=1495288645&upn=l1KXqkv-hzg&mime=audio%2Fwebm&id=o-AANfbbWDU6ST1z8qBYgYMM8w_38v_S7qhFT12LJfzFBo&dur=262.061&source=youtube&keepalive=yes&ip=2001%3A250%3A209%3A2000%3Ad82c%3Abfbf%3A5f8f%3A1e95&requiressl=yes&lmt=1449650115743179&itag=250&ei=5PYfWeilPIbe4gLX4KjIBw&ms=au&mt=1495266922&pl=48&mv=m&clen=2144864&signature=3BE3297CBF9C30977D9A15BD497F08D0A893B373.6255C162D01E0A9654C6217AE1774AC8DE63EA16&key=yt6&mm=31&mn=sn-i3beln7s&gir=yes&sparams=clen%2Cdur%2Cei%2Cgir%2Cid%2Cinitcwndbps%2Cip%2Cipbits%2Citag%2Ckeepalive%2Clmt%2Cmime%2Cmm%2Cmn%2Cms%2Cmv%2Cpl%2Crequiressl%2Csource%2Cupn%2Cexpire&ratebypass=yes", "player_url": null, "ext": "webm", "format_note": "DASH audio", "acodec": "opus", "abr": 70, "filesize": 2144864, "tbr": 78.996, "vcodec": "none", "format": "250 - audio only (DASH audio)", "protocol": "https", "http_headers": {"User-Agent": "Mozilla/5.0 (X11; Linux x86_64; rv:10.0) Gecko/20150101 Firefox/47.0 (Chrome)", "Accept-Charset": "ISO-8859-1,utf-8;q=0.7,*;q=0.7", "Accept": "text/html,application/xhtml+xml,application/xml;q=0.9,*/*;q=0.8", "Accept-Encoding": "gzip, deflate", "Accept-Language": "en-us,en;q=0.5"}}, {"format_id": "140", "url": "https://r2---sn-i3beln7s.googlevideo.com/videoplayback?ipbits=0&initcwndbps=1576250&expire=1495288645&upn=l1KXqkv-hzg&mime=audio%2Fmp4&id=o-AANfbbWDU6ST1z8qBYgYMM8w_38v_S7qhFT12LJfzFBo&dur=262.106&source=youtube&keepalive=yes&ip=2001%3A250%3A209%3A2000%3Ad82c%3Abfbf%3A5f8f%3A1e95&requiressl=yes&lmt=1463798681102978&itag=140&ei=5PYfWeilPIbe4gLX4KjIBw&ms=au&mt=1495266922&pl=48&mv=m&clen=4163601&signature=CBF1608AD06CE97560D218FCA467C928996EF49E.A51B28F2C12C79E762DD187B2CD84748018D367C&key=yt6&mm=31&mn=sn-i3beln7s&gir=yes&sparams=clen%2Cdur%2Cei%2Cgir%2Cid%2Cinitcwndbps%2Cip%2Cipbits%2Citag%2Ckeepalive%2Clmt%2Cmime%2Cmm%2Cmn%2Cms%2Cmv%2Cpl%2Crequiressl%2Csource%2Cupn%2Cexpire&ratebypass=yes", "player_url": null, "ext": "m4a", "format_note": "DASH audio", "acodec": "mp4a.40.2", "abr": 128, "container": "m4a_dash", "filesize": 4163601, "tbr": 128.334, "vcodec": "none", "format": "140 - audio only (DASH audio)", "protocol": "https", "http_headers": {"User-Agent": "Mozilla/5.0 (X11; Linux x86_64; rv:10.0) Gecko/20150101 Firefox/47.0 (Chrome)", "Accept-Charset": "ISO-8859-1,utf-8;q=0.7,*;q=0.7", "Accept": "text/html,application/xhtml+xml,application/xml;q=0.9,*/*;q=0.8", "Accept-Encoding": "gzip, deflate", "Accept-Language": "en-us,en;q=0.5"}}, {"format_id": "171", "url": "https://r2---sn-i3beln7s.googlevideo.com/videoplayback?ipbits=0&initcwndbps=1576250&expire=1495288645&upn=l1KXqkv-hzg&mime=audio%2Fwebm&id=o-AANfbbWDU6ST1z8qBYgYMM8w_38v_S7qhFT12LJfzFBo&dur=262.053&source=youtube&keepalive=yes&ip=2001%3A250%3A209%3A2000%3Ad82c%3Abfbf%3A5f8f%3A1e95&requiressl=yes&lmt=1449650110079070&itag=171&ei=5PYfWeilPIbe4gLX4KjIBw&ms=au&mt=1495266922&pl=48&mv=m&clen=3989733&signature=C7C3097623F8AA8EAAC3FF47AE952E7BDA7AB514.D2EF2CD0376F86FE851BEC4175E856BAA6AF0544&key=yt6&mm=31&mn=sn-i3beln7s&gir=yes&sparams=clen%2Cdur%2Cei%2Cgir%2Cid%2Cinitcwndbps%2Cip%2Cipbits%2Citag%2Ckeepalive%2Clmt%2Cmime%2Cmm%2Cmn%2Cms%2Cmv%2Cpl%2Crequiressl%2Csource%2Cupn%2Cexpire&ratebypass=yes", "player_url": null, "ext": "webm", "acodec": "vorbis", "format_note": "DASH audio", "abr": 128, "filesize": 3989733, "tbr": 135.625, "vcodec": "none", "format": "171 - audio only (DASH audio)", "protocol": "https", "http_headers": {"User-Agent": "Mozilla/5.0 (X11; Linux x86_64; rv:10.0) Gecko/20150101 Firefox/47.0 (Chrome)", "Accept-Charset": "ISO-8859-1,utf-8;q=0.7,*;q=0.7", "Accept": "text/html,application/xhtml+xml,application/xml;q=0.9,*/*;q=0.8", "Accept-Encoding": "gzip, deflate", "Accept-Language": "en-us,en;q=0.5"}}, {"format_id": "251", "url": "https://r2---sn-i3beln7s.googlevideo.com/videoplayback?ipbits=0&initcwndbps=1576250&expire=1495288645&upn=l1KXqkv-hzg&mime=audio%2Fwebm&id=o-AANfbbWDU6ST1z8qBYgYMM8w_38v_S7qhFT12LJfzFBo&dur=262.061&source=youtube&keepalive=yes&ip=2001%3A250%3A209%3A2000%3Ad82c%3Abfbf%3A5f8f%3A1e95&requiressl=yes&lmt=1449650084122520&itag=251&ei=5PYfWeilPIbe4gLX4KjIBw&ms=au&mt=1495266922&pl=48&mv=m&clen=4188732&signature=AA7FBE6F29115197D05D0E01CA119FD3EFC93A36.039400021A1D668F6A3DDCE949A2E2BFC51B997C&key=yt6&mm=31&mn=sn-i3beln7s&gir=yes&sparams=clen%2Cdur%2Cei%2Cgir%2Cid%2Cinitcwndbps%2Cip%2Cipbits%2Citag%2Ckeepalive%2Clmt%2Cmime%2Cmm%2Cmn%2Cms%2Cmv%2Cpl%2Crequiressl%2Csource%2Cupn%2Cexpire&ratebypass=yes", "player_url": null, "ext": "webm", "format_note": "DASH audio", "acodec": "opus", "abr": 160, "filesize": 4188732, "tbr": 149.524, "vcodec": "none", "format": "251 - audio only (DASH audio)", "protocol": "https", "http_headers": {"User-Agent": "Mozilla/5.0 (X11; Linux x86_64; rv:10.0) Gecko/20150101 Firefox/47.0 (Chrome)", "Accept-Charset": "ISO-8859-1,utf-8;q=0.7,*;q=0.7", "Accept": "text/html,application/xhtml+xml,application/xml;q=0.9,*/*;q=0.8", "Accept-Encoding": "gzip, deflate", "Accept-Language": "en-us,en;q=0.5"}}, {"format_id": "160", "url": "https://r2---sn-i3beln7s.googlevideo.com/videoplayback?ipbits=0&initcwndbps=1576250&expire=1495288645&upn=l1KXqkv-hzg&mime=video%2Fmp4&id=o-AANfbbWDU6ST1z8qBYgYMM8w_38v_S7qhFT12LJfzFBo&dur=262.053&source=youtube&keepalive=yes&ip=2001%3A250%3A209%3A2000%3Ad82c%3Abfbf%3A5f8f%3A1e95&requiressl=yes&lmt=1463799127166962&itag=160&ei=5PYfWeilPIbe4gLX4KjIBw&ms=au&mt=1495266922&pl=48&mv=m&clen=3536076&signature=18C065DF3A5A6F69E9F835B68A66A5B6A8B03B1C.0B804028C043946F712B3889B36681DD3FC4F6A6&key=yt6&mm=31&mn=sn-i3beln7s&gir=yes&sparams=clen%2Cdur%2Cei%2Cgir%2Cid%2Cinitcwndbps%2Cip%2Cipbits%2Citag%2Ckeepalive%2Clmt%2Cmime%2Cmm%2Cmn%2Cms%2Cmv%2Cpl%2Crequiressl%2Csource%2Cupn%2Cexpire&ratebypass=yes", "player_url": null, "ext": "mp4", "height": 144, "format_note": "144p", "vcodec": "avc1.4d400c", "filesize": 3536076, "tbr": 112.301, "width": 256, "fps": 24, "acodec": "none", "format": "160 - 256x144 (144p)", "protocol": "https", "http_headers": {"User-Agent": "Mozilla/5.0 (X11; Linux x86_64; rv:10.0) Gecko/20150101 Firefox/47.0 (Chrome)", "Accept-Charset": "ISO-8859-1,utf-8;q=0.7,*;q=0.7", "Accept": "text/html,application/xhtml+xml,application/xml;q=0.9,*/*;q=0.8", "Accept-Encoding": "gzip, deflate", "Accept-Language": "en-us,en;q=0.5"}}, {"format_id": "278", "url": "https://r2---sn-i3beln7s.googlevideo.com/videoplayback?ipbits=0&initcwndbps=1576250&expire=1495288645&upn=l1KXqkv-hzg&mime=video%2Fwebm&id=o-AANfbbWDU6ST1z8qBYgYMM8w_38v_S7qhFT12LJfzFBo&dur=262.012&source=youtube&keepalive=yes&ip=2001%3A250%3A209%3A2000%3Ad82c%3Abfbf%3A5f8f%3A1e95&requiressl=yes&lmt=1449655674472932&itag=278&ei=5PYfWeilPIbe4gLX4KjIBw&ms=au&mt=1495266922&pl=48&mv=m&clen=3251975&signature=22FFEE2F627FBC6EC4A293F99DE80210E1BA3DE3.605A200E6C1D8104D7C776268D40CCBCA2E8F3BF&key=yt6&mm=31&mn=sn-i3beln7s&gir=yes&sparams=clen%2Cdur%2Cei%2Cgir%2Cid%2Cinitcwndbps%2Cip%2Cipbits%2Citag%2Ckeepalive%2Clmt%2Cmime%2Cmm%2Cmn%2Cms%2Cmv%2Cpl%2Crequiressl%2Csource%2Cupn%2Cexpire&ratebypass=yes", "player_url": null, "ext": "webm", "height": 144, "format_note": "144p", "container": "webm", "vcodec": "vp9", "filesize": 3251975, "tbr": 120.238, "width": 256, "fps": 12, "acodec": "none", "format": "278 - 256x144 (144p)", "protocol": "https", "http_headers": {"User-Agent": "Mozilla/5.0 (X11; Linux x86_64; rv:10.0) Gecko/20150101 Firefox/47.0 (Chrome)", "Accept-Charset": "ISO-8859-1,utf-8;q=0.7,*;q=0.7", "Accept": "text/html,application/xhtml+xml,application/xml;q=0.9,*/*;q=0.8", "Accept-Encoding": "gzip, deflate", "Accept-Language": "en-us,en;q=0.5"}}, {"format_id": "133", "url": "https://r2---sn-i3beln7s.googlevideo.com/videoplayback?ipbits=0&initcwndbps=1576250&expire=1495288645&upn=l1KXqkv-hzg&mime=video%2Fmp4&id=o-AANfbbWDU6ST1z8qBYgYMM8w_38v_S7qhFT12LJfzFBo&dur=262.053&source=youtube&keepalive=yes&ip=2001%3A250%3A209%3A2000%3Ad82c%3Abfbf%3A5f8f%3A1e95&requiressl=yes&lmt=1463799127261092&itag=133&ei=5PYfWeilPIbe4gLX4KjIBw&ms=au&mt=1495266922&pl=48&mv=m&clen=7909286&signature=7ADD98E3BB609444D5C42FFA9669C301E23DC26F.F0B45C504CE4E8339108CF79F21E0FDCD8DC2F&key=yt6&mm=31&mn=sn-i3beln7s&gir=yes&sparams=clen%2Cdur%2Cei%2Cgir%2Cid%2Cinitcwndbps%2Cip%2Cipbits%2Citag%2Ckeepalive%2Clmt%2Cmime%2Cmm%2Cmn%2Cms%2Cmv%2Cpl%2Crequiressl%2Csource%2Cupn%2Cexpire&ratebypass=yes", "player_url": null, "ext": "mp4", "height": 240, "format_note": "240p", "vcodec": "avc1.4d4015", "filesize": 7909286, "tbr": 252.37, "width": 426, "fps": 24, "acodec": "none", "format": "133 - 426x240 (240p)", "protocol": "https", "http_headers": {"User-Agent": "Mozilla/5.0 (X11; Linux x86_64; rv:10.0) Gecko/20150101 Firefox/47.0 (Chrome)", "Accept-Charset": "ISO-8859-1,utf-8;q=0.7,*;q=0.7", "Accept": "text/html,application/xhtml+xml,application/xml;q=0.9,*/*;q=0.8", "Accept-Encoding": "gzip, deflate", "Accept-Language": "en-us,en;q=0.5"}}, {"format_id": "242", "url": "https://r2---sn-i3beln7s.googlevideo.com/videoplayback?ipbits=0&initcwndbps=1576250&expire=1495288645&upn=l1KXqkv-hzg&mime=video%2Fwebm&id=o-AANfbbWDU6ST1z8qBYgYMM8w_38v_S7qhFT12LJfzFBo&dur=262.012&source=youtube&keepalive=yes&ip=2001%3A250%3A209%3A2000%3Ad82c%3Abfbf%3A5f8f%3A1e95&requiressl=yes&lmt=1449655673569162&itag=242&ei=5PYfWeilPIbe4gLX4KjIBw&ms=au&mt=1495266922&pl=48&mv=m&clen=7456900&signature=8C7B33AEF9BF59F3337E9088736C204B309FB284.8BC9E10ED274ABAC2FE9A991F088DA76AA960774&key=yt6&mm=31&mn=sn-i3beln7s&gir=yes&sparams=clen%2Cdur%2Cei%2Cgir%2Cid%2Cinitcwndbps%2Cip%2Cipbits%2Citag%2Ckeepalive%2Clmt%2Cmime%2Cmm%2Cmn%2Cms%2Cmv%2Cpl%2Crequiressl%2Csource%2Cupn%2Cexpire&ratebypass=yes", "player_url": null, "ext": "webm", "height": 240, "format_note": "240p", "vcodec": "vp9", "filesize": 7456900, "tbr": 282.81, "width": 426, "fps": 24, "acodec": "none", "format": "242 - 426x240 (240p)", "protocol": "https", "http_headers": {"User-Agent": "Mozilla/5.0 (X11; Linux x86_64; rv:10.0) Gecko/20150101 Firefox/47.0 (Chrome)", "Accept-Charset": "ISO-8859-1,utf-8;q=0.7,*;q=0.7", "Accept": "text/html,application/xhtml+xml,application/xml;q=0.9,*/*;q=0.8", "Accept-Encoding": "gzip, deflate", "Accept-Language": "en-us,en;q=0.5"}}, {"format_id": "243", "url": "https://r2---sn-i3beln7s.googlevideo.com/videoplayback?ipbits=0&initcwndbps=1576250&expire=1495288645&upn=l1KXqkv-hzg&mime=video%2Fwebm&id=o-AANfbbWDU6ST1z8qBYgYMM8w_38v_S7qhFT12LJfzFBo&dur=262.012&source=youtube&keepalive=yes&ip=2001%3A250%3A209%3A2000%3Ad82c%3Abfbf%3A5f8f%3A1e95&requiressl=yes&lmt=1449655675567935&itag=243&ei=5PYfWeilPIbe4gLX4KjIBw&ms=au&mt=1495266922&pl=48&mv=m&clen=13704050&signature=243794DA4D1E1D355592383527E33DB1A8243EC9.160E89E88B3D39FCD73741495154EE3D643F579C&key=yt6&mm=31&mn=sn-i3beln7s&gir=yes&sparams=clen%2Cdur%2Cei%2Cgir%2Cid%2Cinitcwndbps%2Cip%2Cipbits%2Citag%2Ckeepalive%2Clmt%2Cmime%2Cmm%2Cmn%2Cms%2Cmv%2Cpl%2Crequiressl%2Csource%2Cupn%2Cexpire&ratebypass=yes", "player_url": null, "ext": "webm", "height": 360, "format_note": "360p", "vcodec": "vp9", "filesize": 13704050, "tbr": 494.558, "width": 640, "fps": 24, "acodec": "none", "format": "243 - 640x360 (360p)", "protocol": "https", "http_headers": {"User-Agent": "Mozilla/5.0 (X11; Linux x86_64; rv:10.0) Gecko/20150101 Firefox/47.0 (Chrome)", "Accept-Charset": "ISO-8859-1,utf-8;q=0.7,*;q=0.7", "Accept": "text/html,application/xhtml+xml,application/xml;q=0.9,*/*;q=0.8", "Accept-Encoding": "gzip, deflate", "Accept-Language": "en-us,en;q=0.5"}}, {"format_id": "134", "url": "https://r2---sn-i3beln7s.googlevideo.com/videoplayback?ipbits=0&initcwndbps=1576250&expire=1495288645&upn=l1KXqkv-hzg&mime=video%2Fmp4&id=o-AANfbbWDU6ST1z8qBYgYMM8w_38v_S7qhFT12LJfzFBo&dur=262.053&source=youtube&keepalive=yes&ip=2001%3A250%3A209%3A2000%3Ad82c%3Abfbf%3A5f8f%3A1e95&requiressl=yes&lmt=1463799127269022&itag=134&ei=5PYfWeilPIbe4gLX4KjIBw&ms=au&mt=1495266922&pl=48&mv=m&clen=18905331&signature=87EAA0C0794C9297D81CAA2444330BCA6CBBD4E7.3BAF9297183FC9D0AEDFFAE0AE5E0EF830C0D197&key=yt6&mm=31&mn=sn-i3beln7s&gir=yes&sparams=clen%2Cdur%2Cei%2Cgir%2Cid%2Cinitcwndbps%2Cip%2Cipbits%2Citag%2Ckeepalive%2Clmt%2Cmime%2Cmm%2Cmn%2Cms%2Cmv%2Cpl%2Crequiressl%2Csource%2Cupn%2Cexpire&ratebypass=yes", "player_url": null, "ext": "mp4", "height": 360, "format_note": "360p", "vcodec": "avc1.4d401e", "filesize": 18905331, "tbr": 656.494, "width": 640, "fps": 24, "acodec": "none", "format": "134 - 640x360 (360p)", "protocol": "https", "http_headers": {"User-Agent": "Mozilla/5.0 (X11; Linux x86_64; rv:10.0) Gecko/20150101 Firefox/47.0 (Chrome)", "Accept-Charset": "ISO-8859-1,utf-8;q=0.7,*;q=0.7", "Accept": "text/html,application/xhtml+xml,application/xml;q=0.9,*/*;q=0.8", "Accept-Encoding": "gzip, deflate", "Accept-Language": "en-us,en;q=0.5"}}, {"format_id": "244", "url": "https://r2---sn-i3beln7s.googlevideo.com/videoplayback?ipbits=0&initcwndbps=1576250&expire=1495288645&upn=l1KXqkv-hzg&mime=video%2Fwebm&id=o-AANfbbWDU6ST1z8qBYgYMM8w_38v_S7qhFT12LJfzFBo&dur=262.012&source=youtube&keepalive=yes&ip=2001%3A250%3A209%3A2000%3Ad82c%3Abfbf%3A5f8f%3A1e95&requiressl=yes&lmt=1449655675102374&itag=244&ei=5PYfWeilPIbe4gLX4KjIBw&ms=au&mt=1495266922&pl=48&mv=m&clen=25033664&signature=7C48ACE51C4924587849D5FF2F41EED20D1C032C.8FC5A42AAC1F5839D9CAC2A5598696E97FCD67E6&key=yt6&mm=31&mn=sn-i3beln7s&gir=yes&sparams=clen%2Cdur%2Cei%2Cgir%2Cid%2Cinitcwndbps%2Cip%2Cipbits%2Citag%2Ckeepalive%2Clmt%2Cmime%2Cmm%2Cmn%2Cms%2Cmv%2Cpl%2Crequiressl%2Csource%2Cupn%2Cexpire&ratebypass=yes", "player_url": null, "ext": "webm", "height": 480, "format_note": "480p", "vcodec": "vp9", "filesize": 25033664, "tbr": 922.072, "width": 854, "fps": 24, "acodec": "none", "format": "244 - 854x480 (480p)", "protocol": "https", "http_headers": {"User-Agent": "Mozilla/5.0 (X11; Linux x86_64; rv:10.0) Gecko/20150101 Firefox/47.0 (Chrome)", "Accept-Charset": "ISO-8859-1,utf-8;q=0.7,*;q=0.7", "Accept": "text/html,application/xhtml+xml,application/xml;q=0.9,*/*;q=0.8", "Accept-Encoding": "gzip, deflate", "Accept-Language": "en-us,en;q=0.5"}}, {"format_id": "135", "url": "https://r2---sn-i3beln7s.googlevideo.com/videoplayback?ipbits=0&initcwndbps=1576250&expire=1495288645&upn=l1KXqkv-hzg&mime=video%2Fmp4&id=o-AANfbbWDU6ST1z8qBYgYMM8w_38v_S7qhFT12LJfzFBo&dur=262.053&source=youtube&keepalive=yes&ip=2001%3A250%3A209%3A2000%3Ad82c%3Abfbf%3A5f8f%3A1e95&requiressl=yes&lmt=1463799127268268&itag=135&ei=5PYfWeilPIbe4gLX4KjIBw&ms=au&mt=1495266922&pl=48&mv=m&clen=34886848&signature=C1E84E62B6AB93AABC546757003352786AC62338.93CC3A47E254DA99B65B4FDB6F387BEDB80BA6E5&key=yt6&mm=31&mn=sn-i3beln7s&gir=yes&sparams=clen%2Cdur%2Cei%2Cgir%2Cid%2Cinitcwndbps%2Cip%2Cipbits%2Citag%2Ckeepalive%2Clmt%2Cmime%2Cmm%2Cmn%2Cms%2Cmv%2Cpl%2Crequiressl%2Csource%2Cupn%2Cexpire&ratebypass=yes", "player_url": null, "ext": "mp4", "height": 480, "format_note": "480p", "vcodec": "avc1.4d401e", "filesize": 34886848, "tbr": 1184.639, "width": 854, "fps": 24, "acodec": "none", "format": "135 - 854x480 (480p)", "protocol": "https", "http_headers": {"User-Agent": "Mozilla/5.0 (X11; Linux x86_64; rv:10.0) Gecko/20150101 Firefox/47.0 (Chrome)", "Accept-Charset": "ISO-8859-1,utf-8;q=0.7,*;q=0.7", "Accept": "text/html,application/xhtml+xml,application/xml;q=0.9,*/*;q=0.8", "Accept-Encoding": "gzip, deflate", "Accept-Language": "en-us,en;q=0.5"}}, {"format_id": "247", "url": "https://r2---sn-i3beln7s.googlevideo.com/videoplayback?ipbits=0&initcwndbps=1576250&expire=1495288645&upn=l1KXqkv-hzg&mime=video%2Fwebm&id=o-AANfbbWDU6ST1z8qBYgYMM8w_38v_S7qhFT12LJfzFBo&dur=262.012&source=youtube&keepalive=yes&ip=2001%3A250%3A209%3A2000%3Ad82c%3Abfbf%3A5f8f%3A1e95&requiressl=yes&lmt=1449655678269911&itag=247&ei=5PYfWeilPIbe4gLX4KjIBw&ms=au&mt=1495266922&pl=48&mv=m&clen=49141053&signature=40AE49F0AD889911A06D5341779694C79BFB1FEB.756678EDE0971A12547BFB5888BECDD70AD4ABFD&key=yt6&mm=31&mn=sn-i3beln7s&gir=yes&sparams=clen%2Cdur%2Cei%2Cgir%2Cid%2Cinitcwndbps%2Cip%2Cipbits%2Citag%2Ckeepalive%2Clmt%2Cmime%2Cmm%2Cmn%2Cms%2Cmv%2Cpl%2Crequiressl%2Csource%2Cupn%2Cexpire&ratebypass=yes", "player_url": null, "ext": "webm", "height": 720, "format_note": "720p", "vcodec": "vp9", "filesize": 49141053, "tbr": 1764.127, "width": 1280, "fps": 24, "acodec": "none", "format": "247 - 1280x720 (720p)", "protocol": "https", "http_headers": {"User-Agent": "Mozilla/5.0 (X11; Linux x86_64; rv:10.0) Gecko/20150101 Firefox/47.0 (Chrome)", "Accept-Charset": "ISO-8859-1,utf-8;q=0.7,*;q=0.7", "Accept": "text/html,application/xhtml+xml,application/xml;q=0.9,*/*;q=0.8", "Accept-Encoding": "gzip, deflate", "Accept-Language": "en-us,en;q=0.5"}}, {"format_id": "136", "url": "https://r2---sn-i3beln7s.googlevideo.com/videoplayback?ipbits=0&initcwndbps=1576250&expire=1495288645&upn=l1KXqkv-hzg&mime=video%2Fmp4&id=o-AANfbbWDU6ST1z8qBYgYMM8w_38v_S7qhFT12LJfzFBo&dur=262.053&source=youtube&keepalive=yes&ip=2001%3A250%3A209%3A2000%3Ad82c%3Abfbf%3A5f8f%3A1e95&requiressl=yes&lmt=1463799127363978&itag=136&ei=5PYfWeilPIbe4gLX4KjIBw&ms=au&mt=1495266922&pl=48&mv=m&clen=67314323&signature=D55A7AC224594068B14C19B46A62C80E74A1C317.C4F043F51A3AB481C11342D03E5BA1ECF3A7EC68&key=yt6&mm=31&mn=sn-i3beln7s&gir=yes&sparams=clen%2Cdur%2Cei%2Cgir%2Cid%2Cinitcwndbps%2Cip%2Cipbits%2Citag%2Ckeepalive%2Clmt%2Cmime%2Cmm%2Cmn%2Cms%2Cmv%2Cpl%2Crequiressl%2Csource%2Cupn%2Cexpire&ratebypass=yes", "player_url": null, "ext": "mp4", "height": 720, "format_note": "720p", "vcodec": "avc1.4d401f", "filesize": 67314323, "tbr": 2378.559, "width": 1280, "fps": 24, "acodec": "none", "format": "136 - 1280x720 (720p)", "protocol": "https", "http_headers": {"User-Agent": "Mozilla/5.0 (X11; Linux x86_64; rv:10.0) Gecko/20150101 Firefox/47.0 (Chrome)", "Accept-Charset": "ISO-8859-1,utf-8;q=0.7,*;q=0.7", "Accept": "text/html,application/xhtml+xml,application/xml;q=0.9,*/*;q=0.8", "Accept-Encoding": "gzip, deflate", "Accept-Language": "en-us,en;q=0.5"}}, {"format_id": "248", "url": "https://r2---sn-i3beln7s.googlevideo.com/videoplayback?ipbits=0&initcwndbps=1576250&expire=1495288645&upn=l1KXqkv-hzg&mime=video%2Fwebm&id=o-AANfbbWDU6ST1z8qBYgYMM8w_38v_S7qhFT12LJfzFBo&dur=262.012&source=youtube&keepalive=yes&ip=2001%3A250%3A209%3A2000%3Ad82c%3Abfbf%3A5f8f%3A1e95&requiressl=yes&lmt=1449652632832628&itag=248&ei=5PYfWeilPIbe4gLX4KjIBw&ms=au&mt=1495266922&pl=48&mv=m&clen=84949278&signature=25CA3EBF2C8CF9DCC552F92C6EFC3F177DFEE5E7.43508DC47BDFFFE376E8FC49B0BA6ED107353DB2&key=yt6&mm=31&mn=sn-i3beln7s&gir=yes&sparams=clen%2Cdur%2Cei%2Cgir%2Cid%2Cinitcwndbps%2Cip%2Cipbits%2Citag%2Ckeepalive%2Clmt%2Cmime%2Cmm%2Cmn%2Cms%2Cmv%2Cpl%2Crequiressl%2Csource%2Cupn%2Cexpire&ratebypass=yes", "player_url": null, "ext": "webm", "height": 1080, "format_note": "1080p", "vcodec": "vp9", "filesize": 84949278, "tbr": 3219.24, "width": 1920, "fps": 24, "acodec": "none", "format": "248 - 1920x1080 (1080p)", "protocol": "https", "http_headers": {"User-Agent": "Mozilla/5.0 (X11; Linux x86_64; rv:10.0) Gecko/20150101 Firefox/47.0 (Chrome)", "Accept-Charset": "ISO-8859-1,utf-8;q=0.7,*;q=0.7", "Accept": "text/html,application/xhtml+xml,application/xml;q=0.9,*/*;q=0.8", "Accept-Encoding": "gzip, deflate", "Accept-Language": "en-us,en;q=0.5"}}, {"format_id": "137", "url": "https://r2---sn-i3beln7s.googlevideo.com/videoplayback?ipbits=0&initcwndbps=1576250&expire=1495288645&upn=l1KXqkv-hzg&mime=video%2Fmp4&id=o-AANfbbWDU6ST1z8qBYgYMM8w_38v_S7qhFT12LJfzFBo&dur=262.053&source=youtube&keepalive=yes&ip=2001%3A250%3A209%3A2000%3Ad82c%3Abfbf%3A5f8f%3A1e95&requiressl=yes&lmt=1463798960849174&itag=137&ei=5PYfWeilPIbe4gLX4KjIBw&ms=au&mt=1495266922&pl=48&mv=m&clen=120472628&signature=D038B6F0B190062F1A2C99EF66A544E052C3D5FF.7C33845F34AB90803A703B9827770E5580BBA433&key=yt6&mm=31&mn=sn-i3beln7s&gir=yes&sparams=clen%2Cdur%2Cei%2Cgir%2Cid%2Cinitcwndbps%2Cip%2Cipbits%2Citag%2Ckeepalive%2Clmt%2Cmime%2Cmm%2Cmn%2Cms%2Cmv%2Cpl%2Crequiressl%2Csource%2Cupn%2Cexpire&ratebypass=yes", "player_url": null, "ext": "mp4", "height": 1080, "format_note": "1080p", "vcodec": "avc1.640028", "filesize": 120472628, "tbr": 4413.903, "width": 1920, "fps": 24, "acodec": "none", "format": "137 - 1920x1080 (1080p)", "protocol": "https", "http_headers": {"User-Agent": "Mozilla/5.0 (X11; Linux x86_64; rv:10.0) Gecko/20150101 Firefox/47.0 (Chrome)", "Accept-Charset": "ISO-8859-1,utf-8;q=0.7,*;q=0.7", "Accept": "text/html,application/xhtml+xml,application/xml;q=0.9,*/*;q=0.8", "Accept-Encoding": "gzip, deflate", "Accept-Language": "en-us,en;q=0.5"}}, {"format_id": "17", "url": "https://r2---sn-i3beln7s.googlevideo.com/videoplayback?ipbits=0&initcwndbps=1576250&expire=1495288645&upn=l1KXqkv-hzg&mime=video%2F3gpp&id=o-AANfbbWDU6ST1z8qBYgYMM8w_38v_S7qhFT12LJfzFBo&dur=262.246&source=youtube&ip=2001%3A250%3A209%3A2000%3Ad82c%3Abfbf%3A5f8f%3A1e95&requiressl=yes&lmt=1408650352554198&itag=17&ei=5PYfWeilPIbe4gLX4KjIBw&ms=au&mt=1495266922&pl=48&mv=m&clen=2680129&signature=CA73C1C082747CC6B29EBA0C6BCB019207CE3BC1.3F8622F6A63C4437A05268D94A4FD1D50095F601&key=yt6&mm=31&mn=sn-i3beln7s&gir=yes&sparams=clen%2Cdur%2Cei%2Cgir%2Cid%2Cinitcwndbps%2Cip%2Cipbits%2Citag%2Clmt%2Cmime%2Cmm%2Cmn%2Cms%2Cmv%2Cpl%2Crequiressl%2Csource%2Cupn%2Cexpire&ratebypass=yes", "player_url": null, "ext": "3gp", "width": 176, "height": 144, "acodec": "mp4a.40.2", "abr": 24, "vcodec": "mp4v.20.3", "resolution": "176x144", "format_note": "small", "format": "17 - 176x144 (small)", "protocol": "https", "http_headers": {"User-Agent": "Mozilla/5.0 (X11; Linux x86_64; rv:10.0) Gecko/20150101 Firefox/47.0 (Chrome)", "Accept-Charset": "ISO-8859-1,utf-8;q=0.7,*;q=0.7", "Accept": "text/html,application/xhtml+xml,application/xml;q=0.9,*/*;q=0.8", "Accept-Encoding": "gzip, deflate", "Accept-Language": "en-us,en;q=0.5"}}, {"format_id": "36", "url": "https://r2---sn-i3beln7s.googlevideo.com/videoplayback?ipbits=0&initcwndbps=1576250&expire=1495288645&upn=l1KXqkv-hzg&mime=video%2F3gpp&id=o-AANfbbWDU6ST1z8qBYgYMM8w_38v_S7qhFT12LJfzFBo&dur=262.246&source=youtube&ip=2001%3A250%3A209%3A2000%3Ad82c%3Abfbf%3A5f8f%3A1e95&requiressl=yes&lmt=1408650365849617&itag=36&ei=5PYfWeilPIbe4gLX4KjIBw&ms=au&mt=1495266922&pl=48&mv=m&clen=7458196&signature=A9899650A018346E3B7EEF6582FBA7318020EF6B.AAD8D1E2294FE5BA673C62DCF7F9B3E9BCD26B27&key=yt6&mm=31&mn=sn-i3beln7s&gir=yes&sparams=clen%2Cdur%2Cei%2Cgir%2Cid%2Cinitcwndbps%2Cip%2Cipbits%2Citag%2Clmt%2Cmime%2Cmm%2Cmn%2Cms%2Cmv%2Cpl%2Crequiressl%2Csource%2Cupn%2Cexpire&ratebypass=yes", "player_url": null, "ext": "3gp", "width": 320, "acodec": "mp4a.40.2", "vcodec": "mp4v.20.3", "resolution": "320x180", "height": 180, "format_note": "small", "format": "36 - 320x180 (small)", "protocol": "https", "http_headers": {"User-Agent": "Mozilla/5.0 (X11; Linux x86_64; rv:10.0) Gecko/20150101 Firefox/47.0 (Chrome)", "Accept-Charset": "ISO-8859-1,utf-8;q=0.7,*;q=0.7", "Accept": "text/html,application/xhtml+xml,application/xml;q=0.9,*/*;q=0.8", "Accept-Encoding": "gzip, deflate", "Accept-Language": "en-us,en;q=0.5"}}, {"format_id": "43", "url": "https://r2---sn-i3beln7s.googlevideo.com/videoplayback?ratebypass=yes&ipbits=0&initcwndbps=1576250&expire=1495288645&upn=l1KXqkv-hzg&mime=video%2Fwebm&id=o-AANfbbWDU6ST1z8qBYgYMM8w_38v_S7qhFT12LJfzFBo&dur=0.000&source=youtube&ip=2001%3A250%3A209%3A2000%3Ad82c%3Abfbf%3A5f8f%3A1e95&requiressl=yes&lmt=1408660183931630&itag=43&ei=5PYfWeilPIbe4gLX4KjIBw&ms=au&mt=1495266922&pl=48&mv=m&clen=27798396&signature=76172BDE0F979FA4ACFE744435AD5AD038DA41F3.A9F5118F289C8727D1A1BF52D0CDDD045C49FFAE&key=yt6&mm=31&mn=sn-i3beln7s&gir=yes&sparams=clen%2Cdur%2Cei%2Cgir%2Cid%2Cinitcwndbps%2Cip%2Cipbits%2Citag%2Clmt%2Cmime%2Cmm%2Cmn%2Cms%2Cmv%2Cpl%2Cratebypass%2Crequiressl%2Csource%2Cupn%2Cexpire", "player_url": null, "ext": "webm", "width": 640, "height": 360, "acodec": "vorbis", "abr": 128, "vcodec": "vp8.0", "resolution": "640x360", "format_note": "medium", "format": "43 - 640x360 (medium)", "protocol": "https", "http_headers": {"User-Agent": "Mozilla/5.0 (X11; Linux x86_64; rv:10.0) Gecko/20150101 Firefox/47.0 (Chrome)", "Accept-Charset": "ISO-8859-1,utf-8;q=0.7,*;q=0.7", "Accept": "text/html,application/xhtml+xml,application/xml;q=0.9,*/*;q=0.8", "Accept-Encoding": "gzip, deflate", "Accept-Language": "en-us,en;q=0.5"}}, {"format_id": "18", "url": "https://r2---sn-i3beln7s.googlevideo.com/videoplayback?ratebypass=yes&ipbits=0&initcwndbps=1576250&expire=1495288645&upn=l1KXqkv-hzg&mime=video%2Fmp4&id=o-AANfbbWDU6ST1z8qBYgYMM8w_38v_S7qhFT12LJfzFBo&dur=262.106&source=youtube&ip=2001%3A250%3A209%3A2000%3Ad82c%3Abfbf%3A5f8f%3A1e95&requiressl=yes&lmt=1463798826287771&itag=18&ei=5PYfWeilPIbe4gLX4KjIBw&ms=au&mt=1495266922&pl=48&mv=m&clen=23507653&signature=04F80115E72C6EA7AF74D582793CD1A571A0DB63.A2086ECB3A5814675BC147E70A238B44C0AFA2CD&key=yt6&mm=31&mn=sn-i3beln7s&gir=yes&sparams=clen%2Cdur%2Cei%2Cgir%2Cid%2Cinitcwndbps%2Cip%2Cipbits%2Citag%2Clmt%2Cmime%2Cmm%2Cmn%2Cms%2Cmv%2Cpl%2Cratebypass%2Crequiressl%2Csource%2Cupn%2Cexpire", "player_url": null, "ext": "mp4", "width": 640, "height": 360, "acodec": "mp4a.40.2", "abr": 96, "vcodec": "avc1.42001E", "resolution": "640x360", "format_note": "medium", "format": "18 - 640x360 (medium)", "protocol": "https", "http_headers": {"User-Agent": "Mozilla/5.0 (X11; Linux x86_64; rv:10.0) Gecko/20150101 Firefox/47.0 (Chrome)", "Accept-Charset": "ISO-8859-1,utf-8;q=0.7,*;q=0.7", "Accept": "text/html,application/xhtml+xml,application/xml;q=0.9,*/*;q=0.8", "Accept-Encoding": "gzip, deflate", "Accept-Language": "en-us,en;q=0.5"}}, {"format_id": "22", "url": "https://r2---sn-i3beln7s.googlevideo.com/videoplayback?ratebypass=yes&ipbits=0&initcwndbps=1576250&expire=1495288645&upn=l1KXqkv-hzg&sparams=dur%2Cei%2Cid%2Cinitcwndbps%2Cip%2Cipbits%2Citag%2Clmt%2Cmime%2Cmm%2Cmn%2Cms%2Cmv%2Cpl%2Cratebypass%2Crequiressl%2Csource%2Cupn%2Cexpire&id=o-AANfbbWDU6ST1z8qBYgYMM8w_38v_S7qhFT12LJfzFBo&dur=262.106&source=youtube&ip=2001%3A250%3A209%3A2000%3Ad82c%3Abfbf%3A5f8f%3A1e95&requiressl=yes&lmt=1472309785351662&itag=22&ei=5PYfWeilPIbe4gLX4KjIBw&ms=au&mt=1495266922&pl=48&mv=m&signature=D10E35489F9279BA53B4E7330C730EC773354CCB.A203EAC7ED782885203251DCCA79464FE1C6CEE5&key=yt6&mm=31&mn=sn-i3beln7s&mime=video%2Fmp4", "player_url": null, "ext": "mp4", "width": 1280, "height": 720, "acodec": "mp4a.40.2", "abr": 192, "vcodec": "avc1.64001F", "resolution": "1280x720", "format_note": "hd720", "format": "22 - 1280x720 (hd720)", "protocol": "https", "http_headers": {"User-Agent": "Mozilla/5.0 (X11; Linux x86_64; rv:10.0) Gecko/20150101 Firefox/47.0 (Chrome)", "Accept-Charset": "ISO-8859-1,utf-8;q=0.7,*;q=0.7", "Accept": "text/html,application/xhtml+xml,application/xml;q=0.9,*/*;q=0.8", "Accept-Encoding": "gzip, deflate", "Accept-Language": "en-us,en;q=0.5"}}], "is_live": null, "start_time": null, "end_time": null, "series": null, "season_number": null, "episode_number": null, "extractor": "youtube", "webpage_url_basename": "0HDdjwpPM3Y", "extractor_key": "Youtube", "n_entries": 100, "playlist": "most viewed music videos on YouTube.", "playlist_id": "PL8A83124F1D79BD4F", "playlist_title": "most viewed music videos on YouTube.", "playlist_index": 20, "thumbnails": [{"url": "https://i.ytimg.com/vi/0HDdjwpPM3Y/maxresdefault.jpg", "id": "0"}], "display_id": "0HDdjwpPM3Y", "format_id": "22", "url": "https://r2---sn-i3beln7s.googlevideo.com/videoplayback?ratebypass=yes&ipbits=0&initcwndbps=1576250&expire=1495288645&upn=l1KXqkv-hzg&sparams=dur%2Cei%2Cid%2Cinitcwndbps%2Cip%2Cipbits%2Citag%2Clmt%2Cmime%2Cmm%2Cmn%2Cms%2Cmv%2Cpl%2Cratebypass%2Crequiressl%2Csource%2Cupn%2Cexpire&id=o-AANfbbWDU6ST1z8qBYgYMM8w_38v_S7qhFT12LJfzFBo&dur=262.106&source=youtube&ip=2001%3A250%3A209%3A2000%3Ad82c%3Abfbf%3A5f8f%3A1e95&requiressl=yes&lmt=1472309785351662&itag=22&ei=5PYfWeilPIbe4gLX4KjIBw&ms=au&mt=1495266922&pl=48&mv=m&signature=D10E35489F9279BA53B4E7330C730EC773354CCB.A203EAC7ED782885203251DCCA79464FE1C6CEE5&key=yt6&mm=31&mn=sn-i3beln7s&mime=video%2Fmp4", "player_url": null, "ext": "mp4", "width": 1280, "height": 720, "acodec": "mp4a.40.2", "abr": 192, "vcodec": "avc1.64001F", "resolution": "1280x720", "format_note": "hd720", "format": "22 - 1280x720 (hd720)", "protocol": "https", "http_headers": {"User-Agent": "Mozilla/5.0 (X11; Linux x86_64; rv:10.0) Gecko/20150101 Firefox/47.0 (Chrome)", "Accept-Charset": "ISO-8859-1,utf-8;q=0.7,*;q=0.7", "Accept": "text/html,application/xhtml+xml,application/xml;q=0.9,*/*;q=0.8", "Accept-Encoding": "gzip, deflate", "Accept-Language": "en-us,en;q=0.5"}, "fulltitle": "Jessie J, Ariana Grande, Nicki Minaj - Bang Bang ft. Ariana Grande, Nicki Minaj", "_filename": "Jessie J, Ariana Grande, Nicki Minaj - Bang Bang ft. Ariana Grande, Nicki Minaj-0HDdjwpPM3Y.mp4"}